LICENSE
README.md
setup.cfg
setup.py
polarity_pde.egg-info/PKG-INFO
polarity_pde.egg-info/SOURCES.txt
polarity_pde.egg-info/dependency_links.txt
polarity_pde.egg-info/requires.txt
polarity_pde.egg-info/top_level.txt
polaritypde/__init__.py
polaritypde/interactive.py
polaritypde/ode_examples.py
polaritypde/paramspace.py
polaritypde/pde.py
polaritypde/pde_examples.py
polaritypde/solve.py