Metadata-Version: 1.0
Name: polarity-pde
Version: 0.1.2
Summary: Tools for simulating one-dimensional cell polarity PDE models and performing parameter space analysis
Home-page: UNKNOWN
Author: Tom Bland
Author-email: tom_bland@hotmail.co.uk
License: CC BY 4.0
Platform: UNKNOWN
